{
  "project_name": "stratified_rsna_miccai_brain_tumor_mgmt_methylation_single_t2w",
  "entity": "t-jiachentu",
  "extraction_timestamp": "2025-08-15T10:59:26.036982",
  "extraction_version": "0815_v1",
  "runs": [
    {
      "id": "7246389481.66018-e262cdb1-10db",
      "name": "dinov2_pretrained_t2w_2025-07-27_10-12-41",
      "state": "finished",
      "created_at": "2025-07-27T10:13:02Z",
      "updated_at": null,
      "url": "https://microsoft-research.wandb.io/t-jiachentu/stratified_rsna_miccai_brain_tumor_mgmt_methylation_single_t2w/runs/7246389481.66018-e262cdb1-10db",
      "config": {
        "sam": false,
        "fold": "0",
        "task": "Classification",
        "T_max": 300,
        "mixup": false,
        "model": "dinov2",
        "epochs": 50,
        "compile": false,
        "devices": 1,
        "metrics": [
          "f1",
          "balanced_acc",
          "ap",
          "auroc"
        ],
        "subtask": "multiclass",
        "nesterov": false,
        "strategy": "auto",
        "benchmark": false,
        "chpt_path": null,
        "input_dim": 3,
        "optimizer": "AdamW",
        "precision": "16-mixed",
        "scheduler": "CosineAnneal",
        "warmstart": 20,
        "batch_size": 1,
        "cifar_size": false,
        "max_epochs": 300,
        "pretrained": true,
        "save_preds": true,
        "warmstart2": 0,
        "accelerator": "gpu",
        "input_shape": [
          160,
          160,
          160
        ],
        "mixup_alpha": 0.2,
        "num_classes": 2,
        "num_workers": 16,
        "result_plot": "val",
        "adaptive_sam": false,
        "modality_idx": 2,
        "target_shape": [
          224,
          224,
          224
        ],
        "undecay_norm": false,
        "weight_decay": 0.01,
        "data_root_dir": "/mnt/hanoverlimitedwus2/scratch/t-jiachentu/nnssl_data/nnssl_preprocessed/Dataset020_RSNA_MICCAI_BrainTumor",
        "deterministic": false,
        "learning_rate": 1e-05,
        "input_channels": 1,
        "random_batches": false,
        "resnet_dropout": 0,
        "sync_batchnorm": true,
        "apply_shakedrop": false,
        "finetune_method": "full",
        "freeze_backbone": false,
        "label_smoothing": 0.2,
        "test_transforms": null,
        "final_batch_size": 1,
        "stochastic_depth": false,
        "train_transforms": "batchgenerators.get_training_transforms",
        "dinov2_model_name": "facebook/dinov2-base",
        "log_every_n_steps": 10,
        "slice_aggregation": "mean",
        "squeeze_excitation": false,
        "zero_init_residual": false,
        "classification_task": "mgmt_methylation",
        "use_single_modality": true,
        "auto_batch_size_mode": "power",
        "auto_batch_size_steps": 3,
        "prepare_data_per_node": false,
        "accumulate_grad_batches": 1,
        "auto_batch_size_enabled": false,
        "metric_computation_mode": "epochwise",
        "token_aggregation_method": "mean",
        "use_brainiac_preprocessing": true,
        "classification_head_dropout": 0.5
      },
      "summary": {
        "Test/AP": 0.5234910249710083,
        "Test/AUROC": 0.4955074191093445,
        "Test/Balanced_Accuracy": 0.5,
        "Test/F1": 0.33076924085617065,
        "Test/loss": 0.7169657349586487,
        "Train/AP": 0.5054754018783569,
        "Train/AUROC": 0.5,
        "Train/Balanced_Accuracy": 0.5,
        "Train/F1": 0.3210603892803192,
        "Train/loss": "NaN",
        "Val/AP": 0.5183063745498657,
        "Val/AUROC": 0.5,
        "Val/Balanced_Accuracy": 0.5,
        "Val/F1": 0.32163742184638977,
        "Val/loss": "NaN",
        "_runtime": 56832,
        "_step": 1500,
        "_timestamp": 1753668011.7552807,
        "_wandb": "{'runtime': 56832}",
        "epoch": 300,
        "lr-AdamW": 3.1471622649714703e-10,
        "trainer/global_step": 138300,
        "val_ConfusionMatrix_absolute": "{'_type': 'images/separated', 'count': 1, 'filenames': ['media/images/val_ConfusionMatrix_absolute_1497_41d1a6cd28e3cefe4b22.png'], 'format': 'png', 'height': 800, 'width': 800}",
        "val_ConfusionMatrix_normalized": "{'_type': 'images/separated', 'count': 1, 'filenames': ['media/images/val_ConfusionMatrix_normalized_1496_b73695c4df62adfb3baa.png'], 'format': 'png', 'height': 800, 'width': 800}"
      },
      "tags": [],
      "notes": "Stratified DINOV2 pretrained on rsna_miccai_brain_tumor mgmt_methylation with t2w",
      "group": "4540be3e-d088-477f-b853-576a2eddd4bb",
      "job_type": null,
      "system_metrics": {},
      "user": "t-jiachentu",
      "host": null
    },
    {
      "id": "7246389121.88255-007e1cb4-75e9",
      "name": "brainmvp_pretrained_t2w_2025-07-27_10-18-25",
      "state": "finished",
      "created_at": "2025-07-27T10:18:44Z",
      "updated_at": null,
      "url": "https://microsoft-research.wandb.io/t-jiachentu/stratified_rsna_miccai_brain_tumor_mgmt_methylation_single_t2w/runs/7246389121.88255-007e1cb4-75e9",
      "config": {
        "sam": false,
        "fold": "0",
        "task": "Classification",
        "T_max": 300,
        "mixup": false,
        "model": "brainmvp",
        "epochs": 300,
        "compile": false,
        "devices": 1,
        "metrics": [
          "f1",
          "balanced_acc",
          "ap",
          "auroc"
        ],
        "subtask": "multiclass",
        "nesterov": false,
        "strategy": "auto",
        "benchmark": false,
        "input_dim": 3,
        "optimizer": "AdamW",
        "precision": "16-mixed",
        "scheduler": "CosineAnneal",
        "warmstart": 20,
        "batch_size": 4,
        "cifar_size": false,
        "max_epochs": 300,
        "pretrained": true,
        "save_preds": true,
        "warmstart2": 0,
        "accelerator": "gpu",
        "input_shape": [
          160,
          160,
          160
        ],
        "mixup_alpha": 0.2,
        "num_classes": 2,
        "num_workers": 16,
        "result_plot": "val",
        "adaptive_sam": false,
        "dropout_prob": 0.2,
        "modality_idx": 2,
        "target_shape": [
          96,
          96,
          96
        ],
        "undecay_norm": false,
        "weight_decay": 0.01,
        "data_root_dir": "/mnt/hanoverlimitedwus2/scratch/t-jiachentu/nnssl_data/nnssl_preprocessed/Dataset020_RSNA_MICCAI_BrainTumor",
        "deterministic": false,
        "learning_rate": 1e-05,
        "input_channels": 1,
        "random_batches": false,
        "resnet_dropout": 0,
        "sync_batchnorm": true,
        "apply_shakedrop": false,
        "finetune_method": "full",
        "freeze_backbone": false,
        "label_smoothing": 0.2,
        "pretrained_path": "/mnt/hanoverlimitedwus2/scratch/t-jiachentu/nnssl_data/pretrained_ckpts/BrainMVP/BrainMVP_unet.pt",
        "test_transforms": null,
        "final_batch_size": 4,
        "stochastic_depth": false,
        "train_transforms": "batchgenerators.get_training_transforms",
        "log_every_n_steps": 10,
        "squeeze_excitation": false,
        "zero_init_residual": false,
        "classification_task": "mgmt_methylation",
        "use_single_modality": true,
        "auto_batch_size_mode": "power",
        "auto_batch_size_steps": 3,
        "prepare_data_per_node": false,
        "accumulate_grad_batches": 1,
        "auto_batch_size_enabled": true,
        "metric_computation_mode": "epochwise",
        "token_aggregation_method": "cls_token",
        "use_brainiac_preprocessing": true,
        "classification_head_dropout": 0
      },
      "summary": {
        "Test/AP": 0.4546489119529724,
        "Test/AUROC": 0.3977272808551788,
        "Test/Balanced_Accuracy": 0.5235201120376587,
        "Test/F1": 0.4024124443531037,
        "Test/loss": 0.8789549469947815,
        "Train/AP": 0.6759858727455139,
        "Train/AUROC": 0.6748404502868652,
        "Train/Balanced_Accuracy": 0.6330180764198303,
        "Train/F1": 0.6323184370994568,
        "Train/loss": 0.6601002216339111,
        "Val/AP": 0.5791014432907104,
        "Val/AUROC": 0.5734723806381226,
        "Val/Balanced_Accuracy": 0.5812220573425293,
        "Val/F1": 0.5496894121170044,
        "Val/loss": 0.8030337691307068,
        "_runtime": 26258,
        "_step": 1500,
        "_timestamp": 1753637781.070106,
        "_wandb": "{'runtime': 26258}",
        "epoch": 300,
        "lr-AdamW": 3.1471622649714703e-10,
        "trainer/global_step": 34800,
        "val_ConfusionMatrix_absolute": "{'_type': 'images/separated', 'count': 1, 'filenames': ['media/images/val_ConfusionMatrix_absolute_1497_8909a7989ea49870a163.png'], 'format': 'png', 'height': 800, 'width': 800}",
        "val_ConfusionMatrix_normalized": "{'_type': 'images/separated', 'count': 1, 'filenames': ['media/images/val_ConfusionMatrix_normalized_1496_4207c6588ae6b3ceb1b0.png'], 'format': 'png', 'height': 800, 'width': 800}"
      },
      "tags": [],
      "notes": "Stratified BRAINMVP pretrained on rsna_miccai_brain_tumor mgmt_methylation with t2w",
      "group": "f24a5a2b-f1ab-403d-94ed-355da14c9f0a",
      "job_type": null,
      "system_metrics": {},
      "user": "t-jiachentu",
      "host": null
    },
    {
      "id": "7246388751.16076-2ad02569-69e5",
      "name": "brainiac_pretrained_t2w_2025-07-27_10-24-42",
      "state": "finished",
      "created_at": "2025-07-27T10:25:01Z",
      "updated_at": null,
      "url": "https://microsoft-research.wandb.io/t-jiachentu/stratified_rsna_miccai_brain_tumor_mgmt_methylation_single_t2w/runs/7246388751.16076-2ad02569-69e5",
      "config": {
        "sam": false,
        "fold": "0",
        "task": "Classification",
        "T_max": 300,
        "mixup": false,
        "model": "brainiac",
        "epochs": 300,
        "compile": false,
        "devices": 1,
        "metrics": [
          "f1",
          "balanced_acc",
          "ap",
          "auroc"
        ],
        "subtask": "multiclass",
        "nesterov": false,
        "strategy": "auto",
        "benchmark": false,
        "input_dim": 3,
        "optimizer": "AdamW",
        "precision": "16-mixed",
        "scheduler": "CosineAnneal",
        "warmstart": 20,
        "batch_size": 4,
        "cifar_size": false,
        "max_epochs": 300,
        "pretrained": true,
        "save_preds": true,
        "warmstart2": 0,
        "accelerator": "gpu",
        "input_shape": [
          160,
          160,
          160
        ],
        "mixup_alpha": 0.2,
        "num_classes": 2,
        "num_workers": 16,
        "result_plot": "val",
        "adaptive_sam": false,
        "dropout_prob": 0.2,
        "modality_idx": 2,
        "target_shape": [
          128,
          128,
          128
        ],
        "undecay_norm": false,
        "weight_decay": 0.01,
        "data_root_dir": "/mnt/hanoverlimitedwus2/scratch/t-jiachentu/nnssl_data/nnssl_preprocessed/Dataset020_RSNA_MICCAI_BrainTumor",
        "deterministic": false,
        "learning_rate": 1e-05,
        "input_channels": 1,
        "random_batches": false,
        "resnet_dropout": 0,
        "sync_batchnorm": true,
        "apply_shakedrop": false,
        "finetune_method": "full",
        "freeze_backbone": false,
        "label_smoothing": 0.2,
        "pretrained_path": "/mnt/hanoverlimitedwus2/scratch/t-jiachentu/nnssl_data/pretrained_ckpts/BrainIAC/BrainIAC.ckpt",
        "test_transforms": null,
        "final_batch_size": 4,
        "stochastic_depth": false,
        "train_transforms": "batchgenerators.get_training_transforms",
        "log_every_n_steps": 10,
        "squeeze_excitation": false,
        "zero_init_residual": false,
        "classification_task": "mgmt_methylation",
        "use_single_modality": true,
        "auto_batch_size_mode": "power",
        "auto_batch_size_steps": 3,
        "prepare_data_per_node": false,
        "accumulate_grad_batches": 1,
        "auto_batch_size_enabled": true,
        "metric_computation_mode": "epochwise",
        "token_aggregation_method": "cls_token",
        "use_brainiac_preprocessing": true,
        "classification_head_dropout": 0
      },
      "summary": {
        "Test/AP": 0.5103083848953247,
        "Test/AUROC": 0.4878435730934143,
        "Test/Balanced_Accuracy": 0.4830867052078247,
        "Test/F1": 0.4824851155281067,
        "Test/loss": 0.8611690402030945,
        "Train/AP": 0.886181116104126,
        "Train/AUROC": 0.8923811912536621,
        "Train/Balanced_Accuracy": 0.8071317672729492,
        "Train/F1": 0.807873010635376,
        "Train/loss": 0.5334697365760803,
        "Val/AP": 0.5636586546897888,
        "Val/AUROC": 0.5277198553085327,
        "Val/Balanced_Accuracy": 0.4903129637241363,
        "Val/F1": 0.4751131534576416,
        "Val/loss": 1.2265735864639282,
        "_runtime": 71527,
        "_step": 1500,
        "_timestamp": 1753683427.6470094,
        "_wandb": "{'runtime': 71527}",
        "epoch": 300,
        "lr-AdamW": 3.1471622649714703e-10,
        "trainer/global_step": 34800,
        "val_ConfusionMatrix_absolute": "{'_type': 'images/separated', 'count': 1, 'filenames': ['media/images/val_ConfusionMatrix_absolute_1497_52cb0d7f6614371ab7fb.png'], 'format': 'png', 'height': 800, 'width': 800}",
        "val_ConfusionMatrix_normalized": "{'_type': 'images/separated', 'count': 1, 'filenames': ['media/images/val_ConfusionMatrix_normalized_1496_2caaeef377c7fa6c5325.png'], 'format': 'png', 'height': 800, 'width': 800}"
      },
      "tags": [],
      "notes": "Stratified BRAINIAC pretrained on rsna_miccai_brain_tumor mgmt_methylation with t2w",
      "group": "e423e2d9-43a8-4a9e-a22d-69277c6d28b8",
      "job_type": null,
      "system_metrics": {},
      "user": "t-jiachentu",
      "host": null
    },
    {
      "id": "7246388386.91660-447e50a9-a79e",
      "name": "brainiac_scratch_t2w_2025-07-27_10-30-32",
      "state": "finished",
      "created_at": "2025-07-27T10:30:52Z",
      "updated_at": null,
      "url": "https://microsoft-research.wandb.io/t-jiachentu/stratified_rsna_miccai_brain_tumor_mgmt_methylation_single_t2w/runs/7246388386.91660-447e50a9-a79e",
      "config": {
        "sam": false,
        "fold": "0",
        "task": "Classification",
        "T_max": 300,
        "mixup": false,
        "model": "brainiac",
        "epochs": 300,
        "compile": false,
        "devices": 1,
        "metrics": [
          "f1",
          "balanced_acc",
          "ap",
          "auroc"
        ],
        "subtask": "multiclass",
        "nesterov": false,
        "strategy": "auto",
        "benchmark": false,
        "input_dim": 3,
        "optimizer": "AdamW",
        "precision": "16-mixed",
        "scheduler": "CosineAnneal",
        "warmstart": 20,
        "batch_size": 4,
        "cifar_size": false,
        "max_epochs": 300,
        "pretrained": false,
        "save_preds": true,
        "warmstart2": 0,
        "accelerator": "gpu",
        "input_shape": [
          160,
          160,
          160
        ],
        "mixup_alpha": 0.2,
        "num_classes": 2,
        "num_workers": 16,
        "result_plot": "val",
        "adaptive_sam": false,
        "dropout_prob": 0.2,
        "modality_idx": 2,
        "target_shape": [
          128,
          128,
          128
        ],
        "undecay_norm": false,
        "weight_decay": 0.01,
        "data_root_dir": "/mnt/hanoverlimitedwus2/scratch/t-jiachentu/nnssl_data/nnssl_preprocessed/Dataset020_RSNA_MICCAI_BrainTumor",
        "deterministic": false,
        "learning_rate": 1e-05,
        "input_channels": 1,
        "random_batches": false,
        "resnet_dropout": 0,
        "sync_batchnorm": true,
        "apply_shakedrop": false,
        "finetune_method": "full",
        "freeze_backbone": false,
        "label_smoothing": 0.2,
        "pretrained_path": null,
        "test_transforms": null,
        "final_batch_size": 4,
        "stochastic_depth": false,
        "train_transforms": "batchgenerators.get_training_transforms",
        "log_every_n_steps": 10,
        "squeeze_excitation": false,
        "zero_init_residual": false,
        "classification_task": "mgmt_methylation",
        "use_single_modality": true,
        "auto_batch_size_mode": "power",
        "auto_batch_size_steps": 3,
        "prepare_data_per_node": false,
        "accumulate_grad_batches": 1,
        "auto_batch_size_enabled": true,
        "metric_computation_mode": "epochwise",
        "token_aggregation_method": "cls_token",
        "use_brainiac_preprocessing": true,
        "classification_head_dropout": 0
      },
      "summary": {
        "Test/AP": 0.5169926881790161,
        "Test/AUROC": 0.5174418687820435,
        "Test/Balanced_Accuracy": 0.5,
        "Test/F1": 0.33076924085617065,
        "Test/loss": 0.6937241554260254,
        "Train/AP": 0.6681923866271973,
        "Train/AUROC": 0.6638634204864502,
        "Train/Balanced_Accuracy": 0.6018518209457397,
        "Train/F1": 0.6001428365707397,
        "Train/loss": 0.6636327505111694,
        "Val/AP": 0.5169243812561035,
        "Val/AUROC": 0.5016393661499023,
        "Val/Balanced_Accuracy": 0.5076005458831787,
        "Val/F1": 0.4926093816757202,
        "Val/loss": 0.7529321312904358,
        "_runtime": 70685,
        "_step": 1500,
        "_timestamp": 1753682936.3877065,
        "_wandb": "{'runtime': 70685}",
        "epoch": 300,
        "lr-AdamW": 3.1471622649714703e-10,
        "trainer/global_step": 34800,
        "val_ConfusionMatrix_absolute": "{'_type': 'images/separated', 'count': 1, 'filenames': ['media/images/val_ConfusionMatrix_absolute_1497_0ff41ffb20840f3baed1.png'], 'format': 'png', 'height': 800, 'width': 800}",
        "val_ConfusionMatrix_normalized": "{'_type': 'images/separated', 'count': 1, 'filenames': ['media/images/val_ConfusionMatrix_normalized_1496_9ea6404de8f243107f23.png'], 'format': 'png', 'height': 800, 'width': 800}"
      },
      "tags": [],
      "notes": "Stratified BRAINIAC scratch on rsna_miccai_brain_tumor mgmt_methylation with t2w",
      "group": "75f6a5c6-15a2-45cb-9498-44b5957a9715",
      "job_type": null,
      "system_metrics": {},
      "user": "t-jiachentu",
      "host": null
    },
    {
      "id": "7246388023.15501-c1f42b13-eabc",
      "name": "mri_core_pretrained_t2w_2025-07-27_10-31-07",
      "state": "finished",
      "created_at": "2025-07-27T10:31:26Z",
      "updated_at": null,
      "url": "https://microsoft-research.wandb.io/t-jiachentu/stratified_rsna_miccai_brain_tumor_mgmt_methylation_single_t2w/runs/7246388023.15501-c1f42b13-eabc",
      "config": {
        "sam": false,
        "fold": "0",
        "task": "Classification",
        "T_max": 300,
        "mixup": false,
        "model": "mri_core_finetune",
        "epochs": 50,
        "compile": false,
        "devices": 1,
        "metrics": [
          "f1",
          "balanced_acc",
          "ap",
          "auroc"
        ],
        "subtask": "multiclass",
        "nesterov": false,
        "strategy": "auto",
        "benchmark": false,
        "chpt_path": null,
        "input_dim": 3,
        "optimizer": "AdamW",
        "precision": "16-mixed",
        "scheduler": "CosineAnneal",
        "warmstart": 20,
        "batch_size": 1,
        "cifar_size": false,
        "image_size": 224,
        "max_epochs": 300,
        "pretrained": true,
        "save_preds": true,
        "warmstart2": 0,
        "accelerator": "gpu",
        "input_shape": [
          160,
          160,
          160
        ],
        "mixup_alpha": 0.2,
        "num_classes": 2,
        "num_workers": 16,
        "result_plot": "val",
        "adaptive_sam": false,
        "modality_idx": 2,
        "target_shape": [
          160,
          160,
          160
        ],
        "undecay_norm": false,
        "weight_decay": 0.01,
        "data_root_dir": "/mnt/hanoverlimitedwus2/scratch/t-jiachentu/nnssl_data/nnssl_preprocessed/Dataset020_RSNA_MICCAI_BrainTumor",
        "deterministic": false,
        "learning_rate": 1e-05,
        "input_channels": 1,
        "random_batches": false,
        "resnet_dropout": 0,
        "sync_batchnorm": true,
        "apply_shakedrop": false,
        "finetune_method": "full",
        "freeze_backbone": false,
        "label_smoothing": 0.2,
        "pretrained_path": "/mnt/hanoverlimitedwus2/scratch/t-jiachentu/nnssl_data/pretrained_ckpts/mri_core/mri_core_checkpoint.pth",
        "test_transforms": null,
        "final_batch_size": 1,
        "stochastic_depth": false,
        "train_transforms": "batchgenerators.get_training_transforms",
        "log_every_n_steps": 10,
        "slice_aggregation": "mean",
        "squeeze_excitation": false,
        "zero_init_residual": false,
        "classification_task": "mgmt_methylation",
        "use_single_modality": true,
        "auto_batch_size_mode": "power",
        "auto_batch_size_steps": 3,
        "prepare_data_per_node": false,
        "accumulate_grad_batches": 1,
        "auto_batch_size_enabled": false,
        "metric_computation_mode": "epochwise",
        "token_aggregation_method": "mean",
        "classification_head_dropout": 0.5
      },
      "summary": {
        "Test/AP": 0.5914364457130432,
        "Test/AUROC": 0.5739957690238953,
        "Test/Balanced_Accuracy": 0.5,
        "Test/F1": 0.33076924085617065,
        "Test/loss": 0.6937510371208191,
        "Train/AP": 0.4897782802581787,
        "Train/AUROC": 0.4825008511543274,
        "Train/Balanced_Accuracy": 0.49325141310691833,
        "Train/F1": 0.39262187480926514,
        "Train/loss": 0.6932134032249451,
        "Val/AP": 0.5067956447601318,
        "Val/AUROC": 0.4956780970096588,
        "Val/Balanced_Accuracy": 0.49269744753837585,
        "Val/F1": 0.3563218414783478,
        "Val/loss": 0.6923796534538269,
        "_runtime": 125065,
        "_step": 1500,
        "_timestamp": 1753737349.2461483,
        "_wandb": "{'runtime': 125065}",
        "epoch": 300,
        "lr-AdamW": 3.1471622649714703e-10,
        "trainer/global_step": 138300,
        "val_ConfusionMatrix_absolute": "{'_type': 'images/separated', 'count': 1, 'filenames': ['media/images/val_ConfusionMatrix_absolute_1497_083cbea89714d32fb933.png'], 'format': 'png', 'height': 800, 'width': 800}",
        "val_ConfusionMatrix_normalized": "{'_type': 'images/separated', 'count': 1, 'filenames': ['media/images/val_ConfusionMatrix_normalized_1496_492b53918e6af383faf9.png'], 'format': 'png', 'height': 800, 'width': 800}"
      },
      "tags": [],
      "notes": "Stratified MRI_CORE pretrained on rsna_miccai_brain_tumor mgmt_methylation with t2w",
      "group": "039588b9-c438-440e-b3fe-32cd53ce4e3e",
      "job_type": null,
      "system_metrics": {},
      "user": "t-jiachentu",
      "host": null
    },
    {
      "id": "7246387312.14297-920619c0-9e1f",
      "name": "resenc_MDAETrainer_RandomMask_Flow_BS48_2000ep_pretrained_t2w_2025-07-27_10-46-00",
      "state": "finished",
      "created_at": "2025-07-27T10:46:31Z",
      "updated_at": null,
      "url": "https://microsoft-research.wandb.io/t-jiachentu/stratified_rsna_miccai_brain_tumor_mgmt_methylation_single_t2w/runs/7246387312.14297-920619c0-9e1f",
      "config": {
        "sam": false,
        "fold": "0",
        "task": "Classification",
        "T_max": 300,
        "mixup": false,
        "model": "ResEncoder_Classifier",
        "epochs": 300,
        "compile": false,
        "devices": 1,
        "metrics": [
          "f1",
          "balanced_acc",
          "ap",
          "auroc"
        ],
        "subtask": "multiclass",
        "nesterov": false,
        "strategy": "auto",
        "benchmark": false,
        "chpt_path": "/mnt/hanoverlimitedwus2/mri/scratch/t-jiachentu/nnssl_data/nnssl_results/MDAE/Openmind/0705/Dataset005_OpenMind/BaseMDAETrainer_RandomMask_Flow_BS48_2000ep__nnsslPlans__onemmiso/fold_all/checkpoint_best.pth",
        "input_dim": 3,
        "optimizer": "AdamW",
        "precision": "16-mixed",
        "scheduler": "CosineAnneal",
        "warmstart": 20,
        "batch_size": 4,
        "cifar_size": false,
        "max_epochs": 300,
        "pretrained": true,
        "save_preds": true,
        "warmstart2": 0,
        "accelerator": "gpu",
        "input_shape": [
          160,
          160,
          160
        ],
        "mixup_alpha": 0.2,
        "num_classes": 2,
        "num_workers": 16,
        "result_plot": "val",
        "adaptive_sam": false,
        "modality_idx": 2,
        "target_shape": [
          160,
          160,
          160
        ],
        "undecay_norm": false,
        "weight_decay": 0.01,
        "data_root_dir": "/mnt/hanoverlimitedwus2/scratch/t-jiachentu/nnssl_data/nnssl_preprocessed/Dataset020_RSNA_MICCAI_BrainTumor",
        "deterministic": false,
        "learning_rate": 1e-05,
        "input_channels": 1,
        "random_batches": false,
        "resnet_dropout": 0,
        "sync_batchnorm": true,
        "apply_shakedrop": false,
        "finetune_method": "full",
        "freeze_backbone": false,
        "label_smoothing": 0.2,
        "test_transforms": null,
        "final_batch_size": 8,
        "stochastic_depth": false,
        "train_transforms": "batchgenerators.get_training_transforms",
        "log_every_n_steps": 10,
        "squeeze_excitation": false,
        "zero_init_residual": false,
        "classification_task": "mgmt_methylation",
        "use_single_modality": true,
        "auto_batch_size_mode": "power",
        "auto_batch_size_steps": 3,
        "prepare_data_per_node": false,
        "accumulate_grad_batches": 1,
        "auto_batch_size_enabled": true,
        "metric_computation_mode": "epochwise",
        "token_aggregation_method": null,
        "classification_head_dropout": 0.2
      },
      "summary": {
        "Test/AP": 0.49438920617103577,
        "Test/AUROC": 0.4418604373931885,
        "Test/Balanced_Accuracy": 0.4817653298377991,
        "Test/F1": 0.4783477783203125,
        "Test/loss": 0.7428165078163147,
        "Train/AP": 0.972543716430664,
        "Train/AUROC": 0.971533179283142,
        "Train/Balanced_Accuracy": 0.9040378332138062,
        "Train/F1": 0.904226779937744,
        "Train/loss": 0.4396631121635437,
        "Val/AP": 0.5001189708709717,
        "Val/AUROC": 0.49359166622161865,
        "Val/Balanced_Accuracy": 0.4786885380744934,
        "Val/F1": 0.4771634638309479,
        "Val/loss": 1.0041320323944092,
        "_runtime": 44654,
        "_step": 1500,
        "_timestamp": 1753657844.799051,
        "_wandb": "{'runtime': 44654}",
        "epoch": 300,
        "lr-AdamW": 3.1471622649714703e-10,
        "trainer/global_step": 17400,
        "val_ConfusionMatrix_absolute": "{'_type': 'images/separated', 'count': 1, 'filenames': ['media/images/val_ConfusionMatrix_absolute_1497_f08660a11bb1a5ae96a4.png'], 'format': 'png', 'height': 800, 'width': 800}",
        "val_ConfusionMatrix_normalized": "{'_type': 'images/separated', 'count': 1, 'filenames': ['media/images/val_ConfusionMatrix_normalized_1496_0309be8afd38e36a89cc.png'], 'format': 'png', 'height': 800, 'width': 800}"
      },
      "tags": [],
      "notes": "Stratified RESENC_MDAE pretrained on rsna_miccai_brain_tumor mgmt_methylation with t2w",
      "group": "edffb423-6e34-42c9-9dbe-09ff89ab8266",
      "job_type": null,
      "system_metrics": {},
      "user": "t-jiachentu",
      "host": null
    },
    {
      "id": "7246221811.52546-0152c5f6-34e9",
      "name": "resenc_time_conditioned_pretrained_t2w_2025-07-29_09-01-25",
      "state": "finished",
      "created_at": "2025-07-29T09:02:08Z",
      "updated_at": null,
      "url": "https://microsoft-research.wandb.io/t-jiachentu/stratified_rsna_miccai_brain_tumor_mgmt_methylation_single_t2w/runs/7246221811.52546-0152c5f6-34e9",
      "config": {
        "sam": false,
        "fold": "0",
        "task": "Classification",
        "T_max": 300,
        "mixup": false,
        "model": "ResEncTimeConditioned",
        "epochs": 300,
        "compile": false,
        "devices": 1,
        "metrics": [
          "f1",
          "balanced_acc",
          "ap",
          "auroc"
        ],
        "subtask": "multiclass",
        "nesterov": false,
        "strategy": "auto",
        "time_dim": 256,
        "benchmark": false,
        "input_dim": 3,
        "optimizer": "AdamW",
        "precision": "16-mixed",
        "scheduler": "CosineAnneal",
        "warmstart": 20,
        "batch_size": 4,
        "cifar_size": false,
        "max_epochs": 300,
        "pretrained": true,
        "save_preds": true,
        "warmstart2": 0,
        "accelerator": "gpu",
        "input_shape": [
          160,
          160,
          160
        ],
        "mixup_alpha": 0.2,
        "num_classes": 2,
        "num_workers": 16,
        "result_plot": "val",
        "adaptive_sam": false,
        "dropout_rate": 0.5,
        "modality_idx": 2,
        "target_shape": [
          160,
          160,
          160
        ],
        "undecay_norm": false,
        "weight_decay": 0.01,
        "data_root_dir": "/mnt/hanoverlimitedwus2/scratch/t-jiachentu/nnssl_data/nnssl_preprocessed/Dataset020_RSNA_MICCAI_BrainTumor",
        "deterministic": false,
        "learning_rate": 1e-05,
        "freeze_encoder": false,
        "input_channels": 1,
        "random_batches": false,
        "resnet_dropout": 0,
        "sync_batchnorm": true,
        "apply_shakedrop": false,
        "finetune_method": "full",
        "freeze_backbone": false,
        "label_smoothing": 0.2,
        "test_transforms": null,
        "final_batch_size": 4,
        "stochastic_depth": false,
        "train_transforms": "batchgenerators.get_training_transforms",
        "log_every_n_steps": 10,
        "squeeze_excitation": false,
        "zero_init_residual": false,
        "classification_task": "mgmt_methylation",
        "use_single_modality": true,
        "auto_batch_size_mode": "power",
        "auto_batch_size_steps": 3,
        "prepare_data_per_node": false,
        "learned_sinusoidal_dim": 64,
        "accumulate_grad_batches": 1,
        "auto_batch_size_enabled": true,
        "metric_computation_mode": "epochwise",
        "pretrained_encoder_path": "/mnt/hanoverlimitedwus2/mri/scratch/t-jiachentu/nnssl_data/nnssl_results/MDAE/Openmind/0705/Dataset001_BrainMVP/NoiseConditionedMDAETrainer_RandomMask_BS32_2000ep__nnsslPlans__onemmiso/fold_all/checkpoint_best.pth",
        "token_aggregation_method": "cls_token",
        "classification_head_dropout": 0.5
      },
      "summary": {
        "Test/AP": 0.4952996373176574,
        "Test/AUROC": 0.4672304391860962,
        "Test/Balanced_Accuracy": 0.5,
        "Test/F1": 0.33076924085617065,
        "Test/loss": 0.6944891810417175,
        "Train/AP": 0.9345983266830444,
        "Train/AUROC": 0.9396213293075562,
        "Train/Balanced_Accuracy": 0.8820459246635437,
        "Train/F1": 0.8823979496955872,
        "Train/loss": 0.4718207120895386,
        "Val/AP": 0.5477766990661621,
        "Val/AUROC": 0.5305514335632324,
        "Val/Balanced_Accuracy": 0.5205662846565247,
        "Val/F1": 0.5177991390228271,
        "Val/loss": 0.9109251499176024,
        "_runtime": 39237,
        "_step": 1500,
        "_timestamp": 1753818965.8232305,
        "_wandb": "{'runtime': 39237}",
        "epoch": 300,
        "lr-AdamW": 3.1471622649714703e-10,
        "trainer/global_step": 34800,
        "val_ConfusionMatrix_absolute": "{'_type': 'images/separated', 'count': 1, 'filenames': ['media/images/val_ConfusionMatrix_absolute_1497_1cb1322745647e698420.png'], 'format': 'png', 'height': 800, 'width': 800}",
        "val_ConfusionMatrix_normalized": "{'_type': 'images/separated', 'count': 1, 'filenames': ['media/images/val_ConfusionMatrix_normalized_1496_ef8dc526dc64fe43619d.png'], 'format': 'png', 'height': 800, 'width': 800}"
      },
      "tags": [],
      "notes": "Stratified RESENC_TIME_CONDITIONED pretrained on rsna_miccai_brain_tumor mgmt_methylation with t2w",
      "group": "802b2440-deee-4297-b577-3717c51ff042",
      "job_type": null,
      "system_metrics": {},
      "user": "t-jiachentu",
      "host": null
    },
    {
      "id": "7246151360.56887-698e1b9d-f829",
      "name": "resenc_MDAETrainer_RandomMask_Flow_BS48_2000ep_pretrained_t2w_2025-07-30_04-34-25",
      "state": "finished",
      "created_at": "2025-07-30T04:35:04Z",
      "updated_at": null,
      "url": "https://microsoft-research.wandb.io/t-jiachentu/stratified_rsna_miccai_brain_tumor_mgmt_methylation_single_t2w/runs/7246151360.56887-698e1b9d-f829",
      "config": {
        "sam": false,
        "fold": "0",
        "task": "Classification",
        "T_max": 200,
        "mixup": false,
        "model": "ResEncoder_Classifier",
        "epochs": 200,
        "compile": false,
        "devices": 1,
        "metrics": [
          "f1",
          "balanced_acc",
          "ap",
          "auroc"
        ],
        "subtask": "multiclass",
        "nesterov": false,
        "strategy": "auto",
        "benchmark": false,
        "chpt_path": "/mnt/hanoverlimitedwus2/mri/scratch/t-jiachentu/nnssl_data/nnssl_results/MDAE/Openmind/0705/Dataset005_OpenMind/BaseMDAETrainer_RandomMask_Flow_BS48_2000ep__nnsslPlans__onemmiso/fold_all/checkpoint_best.pth",
        "input_dim": 3,
        "optimizer": "AdamW",
        "precision": "16-mixed",
        "scheduler": "CosineAnneal",
        "warmstart": 20,
        "batch_size": 1,
        "cifar_size": false,
        "max_epochs": 200,
        "pretrained": true,
        "save_preds": true,
        "warmstart2": 0,
        "accelerator": "gpu",
        "input_shape": [
          160,
          160,
          160
        ],
        "mixup_alpha": 0.2,
        "num_classes": 2,
        "num_workers": 16,
        "result_plot": "val",
        "adaptive_sam": false,
        "modality_idx": 2,
        "target_shape": [
          160,
          160,
          160
        ],
        "undecay_norm": false,
        "weight_decay": 0.01,
        "data_root_dir": "/mnt/hanoverlimitedwus2/scratch/t-jiachentu/nnssl_data/nnssl_preprocessed/Dataset020_RSNA_MICCAI_BrainTumor",
        "deterministic": false,
        "learning_rate": 5e-06,
        "input_channels": 1,
        "random_batches": false,
        "resnet_dropout": 0,
        "sync_batchnorm": true,
        "apply_shakedrop": false,
        "finetune_method": "full",
        "freeze_backbone": false,
        "label_smoothing": 0.2,
        "test_transforms": null,
        "final_batch_size": 1,
        "stochastic_depth": false,
        "train_transforms": "batchgenerators.get_training_transforms",
        "log_every_n_steps": 10,
        "squeeze_excitation": false,
        "zero_init_residual": false,
        "classification_task": "mgmt_methylation",
        "use_single_modality": true,
        "auto_batch_size_mode": "power",
        "auto_batch_size_steps": 3,
        "prepare_data_per_node": false,
        "accumulate_grad_batches": 1,
        "auto_batch_size_enabled": false,
        "metric_computation_mode": "epochwise",
        "token_aggregation_method": null,
        "classification_head_dropout": 0.2
      },
      "summary": {
        "Test/AP": 0.5134804248809814,
        "Test/AUROC": 0.5,
        "Test/Balanced_Accuracy": 0.5121564269065857,
        "Test/F1": 0.3958333432674408,
        "Test/loss": 0.7118430137634277,
        "Train/AP": 0.8537641763687134,
        "Train/AUROC": 0.8550137281417847,
        "Train/Balanced_Accuracy": 0.7643277645111084,
        "Train/F1": 0.764662504196167,
        "Train/loss": 0.565205454826355,
        "Val/AP": 0.5278761982917786,
        "Val/AUROC": 0.4953800439834595,
        "Val/Balanced_Accuracy": 0.5050670504570007,
        "Val/F1": 0.5041619539260864,
        "Val/loss": 0.8162417411804199,
        "_runtime": 29498,
        "_step": 1000,
        "_timestamp": 1753879599.6267192,
        "_wandb": "{'runtime': 29498}",
        "epoch": 200,
        "lr-AdamW": 3.8076210902182607e-10,
        "trainer/global_step": 92200,
        "val_ConfusionMatrix_absolute": "{'_type': 'images/separated', 'count': 1, 'filenames': ['media/images/val_ConfusionMatrix_absolute_997_9ffafdab9634b00233fc.png'], 'format': 'png', 'height': 800, 'width': 800}",
        "val_ConfusionMatrix_normalized": "{'_type': 'images/separated', 'count': 1, 'filenames': ['media/images/val_ConfusionMatrix_normalized_996_af87a011e4d23a5250ad.png'], 'format': 'png', 'height': 800, 'width': 800}"
      },
      "tags": [],
      "notes": "Stratified RESENC_MDAE pretrained on rsna_miccai_brain_tumor mgmt_methylation with t2w",
      "group": "5f5fd19f-4aea-42ce-94b6-c5fc49b65bda",
      "job_type": null,
      "system_metrics": {},
      "user": "t-jiachentu",
      "host": null
    },
    {
      "id": "7246149414.26717-551e022b-2eb2",
      "name": "resenc_time_conditioned_pretrained_t2w_2025-07-30_04-56-18",
      "state": "finished",
      "created_at": "2025-07-30T04:56:52Z",
      "updated_at": null,
      "url": "https://microsoft-research.wandb.io/t-jiachentu/stratified_rsna_miccai_brain_tumor_mgmt_methylation_single_t2w/runs/7246149414.26717-551e022b-2eb2",
      "config": {
        "sam": false,
        "fold": "0",
        "task": "Classification",
        "T_max": 200,
        "mixup": false,
        "model": "ResEncTimeConditioned",
        "epochs": 200,
        "compile": false,
        "devices": 1,
        "metrics": [
          "f1",
          "balanced_acc",
          "ap",
          "auroc"
        ],
        "subtask": "multiclass",
        "nesterov": false,
        "strategy": "auto",
        "time_dim": 256,
        "benchmark": false,
        "input_dim": 3,
        "optimizer": "AdamW",
        "precision": "16-mixed",
        "scheduler": "CosineAnneal",
        "warmstart": 20,
        "batch_size": 1,
        "cifar_size": false,
        "max_epochs": 200,
        "pretrained": true,
        "save_preds": true,
        "warmstart2": 0,
        "accelerator": "gpu",
        "input_shape": [
          160,
          160,
          160
        ],
        "mixup_alpha": 0.2,
        "num_classes": 2,
        "num_workers": 16,
        "result_plot": "val",
        "adaptive_sam": false,
        "dropout_rate": 0.5,
        "modality_idx": 2,
        "target_shape": [
          160,
          160,
          160
        ],
        "undecay_norm": false,
        "weight_decay": 0.01,
        "data_root_dir": "/mnt/hanoverlimitedwus2/scratch/t-jiachentu/nnssl_data/nnssl_preprocessed/Dataset020_RSNA_MICCAI_BrainTumor",
        "deterministic": false,
        "learning_rate": 5e-06,
        "freeze_encoder": false,
        "input_channels": 1,
        "random_batches": false,
        "resnet_dropout": 0,
        "sync_batchnorm": true,
        "apply_shakedrop": false,
        "finetune_method": "full",
        "freeze_backbone": false,
        "label_smoothing": 0.2,
        "test_transforms": null,
        "final_batch_size": 1,
        "stochastic_depth": false,
        "train_transforms": "batchgenerators.get_training_transforms",
        "log_every_n_steps": 10,
        "squeeze_excitation": false,
        "zero_init_residual": false,
        "classification_task": "mgmt_methylation",
        "use_single_modality": true,
        "auto_batch_size_mode": "power",
        "auto_batch_size_steps": 3,
        "prepare_data_per_node": false,
        "learned_sinusoidal_dim": 64,
        "accumulate_grad_batches": 1,
        "auto_batch_size_enabled": false,
        "metric_computation_mode": "epochwise",
        "pretrained_encoder_path": "/mnt/hanoverlimitedwus2/mri/scratch/t-jiachentu/nnssl_data/nnssl_results/MDAE/Openmind/0705/Dataset001_BrainMVP/NoiseConditionedMDAETrainer_RandomMask_BS32_2000ep__nnsslPlans__onemmiso/fold_all/checkpoint_best.pth",
        "token_aggregation_method": "cls_token",
        "classification_head_dropout": 0.5
      },
      "summary": {
        "Test/AP": 0.5011169910430908,
        "Test/AUROC": 0.4949788749217987,
        "Test/Balanced_Accuracy": 0.5158562660217285,
        "Test/F1": 0.5093985199928284,
        "Test/loss": 0.693345308303833,
        "Train/AP": 0.7278532981872559,
        "Train/AUROC": 0.7503869533538818,
        "Train/Balanced_Accuracy": 0.7008815407752991,
        "Train/F1": 0.7011946439743042,
        "Train/loss": 0.632064163684845,
        "Val/AP": 0.5574092864990234,
        "Val/AUROC": 0.514754056930542,
        "Val/Balanced_Accuracy": 0.4850968718528747,
        "Val/F1": 0.4802156984806061,
        "Val/loss": 0.7330580949783325,
        "_runtime": 32945,
        "_step": 1000,
        "_timestamp": 1753884354.0375924,
        "_wandb": "{'runtime': 32945}",
        "epoch": 200,
        "lr-AdamW": 3.8076210902182607e-10,
        "trainer/global_step": 92200,
        "val_ConfusionMatrix_absolute": "{'_type': 'images/separated', 'count': 1, 'filenames': ['media/images/val_ConfusionMatrix_absolute_997_be18987adbd1abbfda61.png'], 'format': 'png', 'height': 800, 'width': 800}",
        "val_ConfusionMatrix_normalized": "{'_type': 'images/separated', 'count': 1, 'filenames': ['media/images/val_ConfusionMatrix_normalized_996_073bbcf5fa29072705d0.png'], 'format': 'png', 'height': 800, 'width': 800}"
      },
      "tags": [],
      "notes": "Stratified RESENC_TIME_CONDITIONED pretrained on rsna_miccai_brain_tumor mgmt_methylation with t2w",
      "group": "d28b9f8c-0c13-4675-8091-bb549d398069",
      "job_type": null,
      "system_metrics": {},
      "user": "t-jiachentu",
      "host": null
    },
    {
      "id": "7246128252.32704-a6e3e7ed-8ab3",
      "name": "resenc_MDAETrainer_RandomMask_Flow_BS48_2000ep_pretrained_t2w_2025-07-30_10-40-48",
      "state": "finished",
      "created_at": "2025-07-30T10:41:24Z",
      "updated_at": null,
      "url": "https://microsoft-research.wandb.io/t-jiachentu/stratified_rsna_miccai_brain_tumor_mgmt_methylation_single_t2w/runs/7246128252.32704-a6e3e7ed-8ab3",
      "config": {
        "sam": false,
        "fold": "0",
        "task": "Classification",
        "T_max": 200,
        "mixup": false,
        "model": "ResEncoder_Classifier",
        "epochs": 200,
        "compile": false,
        "devices": 1,
        "metrics": [
          "f1",
          "balanced_acc",
          "ap",
          "auroc"
        ],
        "subtask": "multiclass",
        "nesterov": false,
        "strategy": "auto",
        "benchmark": false,
        "chpt_path": "/mnt/hanoverlimitedwus2/mri/scratch/t-jiachentu/nnssl_data/nnssl_results/MDAE/Openmind/0705/Dataset005_OpenMind/BaseMDAETrainer_RandomMask_Flow_BS48_2000ep__nnsslPlans__onemmiso/fold_all/checkpoint_best.pth",
        "input_dim": 3,
        "optimizer": "AdamW",
        "precision": "16-mixed",
        "scheduler": "CosineAnneal",
        "warmstart": 20,
        "batch_size": 1,
        "cifar_size": false,
        "max_epochs": 200,
        "pretrained": true,
        "save_preds": true,
        "warmstart2": 0,
        "accelerator": "gpu",
        "input_shape": [
          160,
          160,
          160
        ],
        "mixup_alpha": 0.2,
        "num_classes": 2,
        "num_workers": 16,
        "result_plot": "val",
        "adaptive_sam": false,
        "modality_idx": 2,
        "target_shape": [
          160,
          160,
          160
        ],
        "undecay_norm": false,
        "weight_decay": 0.01,
        "data_root_dir": "/mnt/hanoverlimitedwus2/scratch/t-jiachentu/nnssl_data/nnssl_preprocessed/Dataset020_RSNA_MICCAI_BrainTumor",
        "deterministic": false,
        "learning_rate": 5e-06,
        "input_channels": 1,
        "random_batches": false,
        "resnet_dropout": 0,
        "sync_batchnorm": true,
        "apply_shakedrop": false,
        "finetune_method": "full",
        "freeze_backbone": false,
        "label_smoothing": 0.2,
        "test_transforms": null,
        "final_batch_size": 1,
        "stochastic_depth": false,
        "train_transforms": "batchgenerators.get_training_transforms",
        "log_every_n_steps": 10,
        "squeeze_excitation": false,
        "zero_init_residual": false,
        "classification_task": "mgmt_methylation",
        "use_single_modality": true,
        "auto_batch_size_mode": "power",
        "auto_batch_size_steps": 3,
        "prepare_data_per_node": false,
        "accumulate_grad_batches": 1,
        "auto_batch_size_enabled": false,
        "metric_computation_mode": "epochwise",
        "token_aggregation_method": null,
        "classification_head_dropout": 0.2
      },
      "summary": {
        "Test/AP": 0.5134804248809814,
        "Test/AUROC": 0.5,
        "Test/Balanced_Accuracy": 0.5121564269065857,
        "Test/F1": 0.3958333432674408,
        "Test/loss": 0.7118430137634277,
        "Train/AP": 0.8537641763687134,
        "Train/AUROC": 0.8550137281417847,
        "Train/Balanced_Accuracy": 0.7643277645111084,
        "Train/F1": 0.764662504196167,
        "Train/loss": 0.565205454826355,
        "Val/AP": 0.5278761982917786,
        "Val/AUROC": 0.4953800439834595,
        "Val/Balanced_Accuracy": 0.5050670504570007,
        "Val/F1": 0.5041619539260864,
        "Val/loss": 0.8162417411804199,
        "_runtime": 29574,
        "_step": 1000,
        "_timestamp": 1753901652.9171162,
        "_wandb": "{'runtime': 29574}",
        "epoch": 200,
        "lr-AdamW": 3.8076210902182607e-10,
        "trainer/global_step": 92200,
        "val_ConfusionMatrix_absolute": "{'_type': 'images/separated', 'count': 1, 'filenames': ['media/images/val_ConfusionMatrix_absolute_997_9ffafdab9634b00233fc.png'], 'format': 'png', 'height': 800, 'width': 800}",
        "val_ConfusionMatrix_normalized": "{'_type': 'images/separated', 'count': 1, 'filenames': ['media/images/val_ConfusionMatrix_normalized_996_af87a011e4d23a5250ad.png'], 'format': 'png', 'height': 800, 'width': 800}"
      },
      "tags": [],
      "notes": "Stratified RESENC_MDAE pretrained on rsna_miccai_brain_tumor mgmt_methylation with t2w",
      "group": "5559bc9d-cf95-4f09-8c8e-aa70418d6ee8",
      "job_type": null,
      "system_metrics": {},
      "user": "t-jiachentu",
      "host": null
    },
    {
      "id": "7246127172.16670-91af963b-0e60",
      "name": "resenc_time_conditioned_pretrained_t2w_2025-07-30_10-59-10",
      "state": "finished",
      "created_at": "2025-07-30T10:59:46Z",
      "updated_at": null,
      "url": "https://microsoft-research.wandb.io/t-jiachentu/stratified_rsna_miccai_brain_tumor_mgmt_methylation_single_t2w/runs/7246127172.16670-91af963b-0e60",
      "config": {
        "sam": false,
        "fold": "0",
        "task": "Classification",
        "T_max": 200,
        "mixup": false,
        "model": "ResEncTimeConditioned",
        "epochs": 200,
        "compile": false,
        "devices": 1,
        "metrics": [
          "f1",
          "balanced_acc",
          "ap",
          "auroc"
        ],
        "subtask": "multiclass",
        "nesterov": false,
        "strategy": "auto",
        "time_dim": 256,
        "benchmark": false,
        "input_dim": 3,
        "optimizer": "AdamW",
        "precision": "16-mixed",
        "scheduler": "CosineAnneal",
        "warmstart": 20,
        "batch_size": 1,
        "cifar_size": false,
        "max_epochs": 200,
        "pretrained": true,
        "save_preds": true,
        "warmstart2": 0,
        "accelerator": "gpu",
        "input_shape": [
          160,
          160,
          160
        ],
        "mixup_alpha": 0.2,
        "num_classes": 2,
        "num_workers": 16,
        "result_plot": "val",
        "adaptive_sam": false,
        "dropout_rate": 0.5,
        "modality_idx": 2,
        "target_shape": [
          160,
          160,
          160
        ],
        "undecay_norm": false,
        "weight_decay": 0.01,
        "data_root_dir": "/mnt/hanoverlimitedwus2/scratch/t-jiachentu/nnssl_data/nnssl_preprocessed/Dataset020_RSNA_MICCAI_BrainTumor",
        "deterministic": false,
        "learning_rate": 5e-06,
        "freeze_encoder": false,
        "input_channels": 1,
        "random_batches": false,
        "resnet_dropout": 0,
        "sync_batchnorm": true,
        "apply_shakedrop": false,
        "finetune_method": "full",
        "freeze_backbone": false,
        "label_smoothing": 0.2,
        "test_transforms": null,
        "final_batch_size": 1,
        "stochastic_depth": false,
        "train_transforms": "batchgenerators.get_training_transforms",
        "log_every_n_steps": 10,
        "squeeze_excitation": false,
        "zero_init_residual": false,
        "classification_task": "mgmt_methylation",
        "use_single_modality": true,
        "auto_batch_size_mode": "power",
        "auto_batch_size_steps": 3,
        "prepare_data_per_node": false,
        "learned_sinusoidal_dim": 64,
        "accumulate_grad_batches": 1,
        "auto_batch_size_enabled": false,
        "metric_computation_mode": "epochwise",
        "pretrained_encoder_path": "/mnt/hanoverlimitedwus2/mri/scratch/t-jiachentu/nnssl_data/nnssl_results/MDAE/Openmind/0705/Dataset001_BrainMVP/NoiseConditionedMDAETrainer_RandomMask_BS32_2000ep__nnsslPlans__onemmiso/fold_all/checkpoint_best.pth",
        "token_aggregation_method": "cls_token",
        "classification_head_dropout": 0.5
      },
      "summary": {
        "Test/AP": 0.5264694690704346,
        "Test/AUROC": 0.4970930218696594,
        "Test/Balanced_Accuracy": 0.5,
        "Test/F1": 0.33076924085617065,
        "Test/loss": 0.6951991319656372,
        "Train/AP": 0.779821515083313,
        "Train/AUROC": 0.8001567125320435,
        "Train/Balanced_Accuracy": 0.7394665479660034,
        "Train/F1": 0.7375221848487854,
        "Train/loss": 0.6000140905380249,
        "Val/AP": 0.498857319355011,
        "Val/AUROC": 0.4895678162574768,
        "Val/Balanced_Accuracy": 0.5013412833213806,
        "Val/F1": 0.5,
        "Val/loss": 0.8103377819061279,
        "_runtime": 34072,
        "_step": 1000,
        "_timestamp": 1753907251.486325,
        "_wandb": "{'runtime': 34072}",
        "epoch": 200,
        "lr-AdamW": 3.8076210902182607e-10,
        "trainer/global_step": 92200,
        "val_ConfusionMatrix_absolute": "{'_type': 'images/separated', 'count': 1, 'filenames': ['media/images/val_ConfusionMatrix_absolute_997_60986efc20fffedbb78b.png'], 'format': 'png', 'height': 800, 'width': 800}",
        "val_ConfusionMatrix_normalized": "{'_type': 'images/separated', 'count': 1, 'filenames': ['media/images/val_ConfusionMatrix_normalized_996_d7e4468cc291c1c8c42d.png'], 'format': 'png', 'height': 800, 'width': 800}"
      },
      "tags": [],
      "notes": "Stratified RESENC_TIME_CONDITIONED pretrained on rsna_miccai_brain_tumor mgmt_methylation with t2w",
      "group": "8a732713-45e2-4606-bb7c-adc61f186004",
      "job_type": null,
      "system_metrics": {},
      "user": "t-jiachentu",
      "host": null
    }
  ],
  "project_metadata": {
    "created_at": "2025-07-27T10:13:02Z",
    "updated_at": null,
    "description": null
  },
  "statistics": {
    "total_runs": 11,
    "completed_runs": 11,
    "failed_runs": 0,
    "running_runs": 0
  }
}